src/__init__.py
src/omniflow/Measurement.py
src/omniflow/__init__.py
src/omniflow/_queries.py
src/omniflow/_utils.py
omniflow-0.1.1.dist-info/LICENSE
omniflow-0.1.1.dist-info/METADATA
omniflow-0.1.1.dist-info/WHEEL
omniflow-0.1.1.dist-info/top_level.txt
omniflow-0.1.1.dist-info/RECORD
