Metadata-Version: 2.2
Name: omniflow
Version: 0.1.1
Summary: OMOP CDM data harmonization and quality control tool
Home-page: https://github.com/bicklab/omniflow
Author: James Brogan
Author-email: james.brogan@vumc.org
Classifier: Programming Language :: Python :: 3
Classifier: Programming Language :: Python :: 3.9
Classifier: License :: OSI Approved :: MIT License
Classifier: Operating System :: OS Independent
Requires-Python: >=3.6
License-File: LICENSE
Requires-Dist: polars
Requires-Dist: pyarrow
Dynamic: author
Dynamic: author-email
Dynamic: classifier
Dynamic: description
Dynamic: description-content-type
Dynamic: home-page
Dynamic: requires-dist
Dynamic: requires-python
Dynamic: summary
